<?xml version="1.0" encoding="UTF-8"?>
<MetaDataObject xmlns="http://v8.1c.ru/8.3/MDClasses" xmlns:app="http://v8.1c.ru/8.2/managed-application/core" xmlns:cfg="http://v8.1c.ru/8.1/data/enterprise/current-config" xmlns:cmi="http://v8.1c.ru/8.2/managed-application/cmi" xmlns:ent="http://v8.1c.ru/8.1/data/enterprise" xmlns:lf="http://v8.1c.ru/8.2/managed-application/logform" xmlns:style="http://v8.1c.ru/8.1/data/ui/style" xmlns:sys="http://v8.1c.ru/8.1/data/ui/fonts/system" xmlns:v8="http://v8.1c.ru/8.1/data/core" xmlns:v8ui="http://v8.1c.ru/8.1/data/ui" xmlns:web="http://v8.1c.ru/8.1/data/ui/colors/web" xmlns:win="http://v8.1c.ru/8.1/data/ui/colors/windows" xmlns:xen="http://v8.1c.ru/8.3/xcf/enums" xmlns:xpr="http://v8.1c.ru/8.3/xcf/predef" xmlns:xr="http://v8.1c.ru/8.3/xcf/readable" xmlns:xs="http://www.w3.org/2001/XMLSchema" xmlns:xsi="http://www.w3.org/2001/XMLSchema-instance" version="2.4">
	<Constant uuid="a51889b6-a62b-431c-a92e-507ad22c5a06">
		<InternalInfo>
			<xr:GeneratedType name="ConstantManager.ИспользоватьСинхронизациюДанных" category="Manager">
				<xr:TypeId>c4905d43-1f17-473b-af66-e4e7c9952a9c</xr:TypeId>
				<xr:ValueId>46026e18-9b6e-4c61-8a3b-781c3083a059</xr:ValueId>
			</xr:GeneratedType>
			<xr:GeneratedType name="ConstantValueManager.ИспользоватьСинхронизациюДанных" category="ValueManager">
				<xr:TypeId>e8b8ee62-1cf9-411e-8750-e9948c12960f</xr:TypeId>
				<xr:ValueId>4d3c0878-1a98-409b-be27-d620881bbbee</xr:ValueId>
			</xr:GeneratedType>
		</InternalInfo>
		<Properties>
			<Name>ИспользоватьСинхронизациюДанных</Name>
			<Synonym>
				<v8:item>
					<v8:lang>ru</v8:lang>
					<v8:content>Использовать синхронизацию данных</v8:content>
				</v8:item>
			</Synonym>
			<Comment/>
			<Type>
				<v8:Type>xs:boolean</v8:Type>
			</Type>
			<UseStandardCommands>false</UseStandardCommands>
			<DefaultForm/>
			<ExtendedPresentation/>
			<Explanation/>
			<PasswordMode>false</PasswordMode>
			<Format/>
			<EditFormat/>
			<ToolTip/>
			<MarkNegatives>false</MarkNegatives>
			<Mask/>
			<MultiLine>false</MultiLine>
			<ExtendedEdit>false</ExtendedEdit>
			<MinValue xsi:nil="true"/>
			<MaxValue xsi:nil="true"/>
			<FillChecking>DontCheck</FillChecking>
			<ChoiceFoldersAndItems>Items</ChoiceFoldersAndItems>
			<ChoiceParameterLinks/>
			<ChoiceParameters/>
			<QuickChoice>Auto</QuickChoice>
			<ChoiceForm/>
			<LinkByType/>
			<ChoiceHistoryOnInput>Auto</ChoiceHistoryOnInput>
			<DataLockControlMode>Managed</DataLockControlMode>
		</Properties>
	</Constant>
</MetaDataObject>