<?xml version="1.0" encoding="UTF-8"?>
<MetaDataObject xmlns="http://v8.1c.ru/8.3/MDClasses" xmlns:app="http://v8.1c.ru/8.2/managed-application/core" xmlns:cfg="http://v8.1c.ru/8.1/data/enterprise/current-config" xmlns:cmi="http://v8.1c.ru/8.2/managed-application/cmi" xmlns:ent="http://v8.1c.ru/8.1/data/enterprise" xmlns:lf="http://v8.1c.ru/8.2/managed-application/logform" xmlns:style="http://v8.1c.ru/8.1/data/ui/style" xmlns:sys="http://v8.1c.ru/8.1/data/ui/fonts/system" xmlns:v8="http://v8.1c.ru/8.1/data/core" xmlns:v8ui="http://v8.1c.ru/8.1/data/ui" xmlns:web="http://v8.1c.ru/8.1/data/ui/colors/web" xmlns:win="http://v8.1c.ru/8.1/data/ui/colors/windows" xmlns:xen="http://v8.1c.ru/8.3/xcf/enums" xmlns:xpr="http://v8.1c.ru/8.3/xcf/predef" xmlns:xr="http://v8.1c.ru/8.3/xcf/readable" xmlns:xs="http://www.w3.org/2001/XMLSchema" xmlns:xsi="http://www.w3.org/2001/XMLSchema-instance" version="2.4">
	<Task uuid="4ddd9856-671d-4ca6-af4a-0521a95ef5d7">
		<InternalInfo>
			<xr:GeneratedType name="TaskObject.ЗадачиПользователя" category="Object">
				<xr:TypeId>d97330ed-090b-45d2-8571-5af2b5afb55a</xr:TypeId>
				<xr:ValueId>fa1e9bc3-2e9e-448f-bf5b-70f776ceaf69</xr:ValueId>
			</xr:GeneratedType>
			<xr:GeneratedType name="TaskRef.ЗадачиПользователя" category="Ref">
				<xr:TypeId>20f72af0-6da1-48ff-8299-1e0a5ee6f0f6</xr:TypeId>
				<xr:ValueId>7a1a347a-f6bc-4726-a775-e75ad42a44d7</xr:ValueId>
			</xr:GeneratedType>
			<xr:GeneratedType name="TaskSelection.ЗадачиПользователя" category="Selection">
				<xr:TypeId>a73d6f55-6c2f-4f79-8120-ea1d95cfca72</xr:TypeId>
				<xr:ValueId>f55345a0-ff14-4a01-975b-965738ba8405</xr:ValueId>
			</xr:GeneratedType>
			<xr:GeneratedType name="TaskList.ЗадачиПользователя" category="List">
				<xr:TypeId>8a22e760-c5e4-4039-8bb7-c4c8cd1a74ca</xr:TypeId>
				<xr:ValueId>73f6d835-b5a5-4a0e-9783-336e6e770a5d</xr:ValueId>
			</xr:GeneratedType>
			<xr:GeneratedType name="TaskManager.ЗадачиПользователя" category="Manager">
				<xr:TypeId>4f97dc83-3fdb-49bf-b7dc-e526c4728a86</xr:TypeId>
				<xr:ValueId>9357afa4-e096-4fe9-bc29-532edca6387c</xr:ValueId>
			</xr:GeneratedType>
		</InternalInfo>
		<Properties>
			<Name>ЗадачиПользователя</Name>
			<Synonym>
				<v8:item>
					<v8:lang>ru</v8:lang>
					<v8:content>Задачи пользователя</v8:content>
				</v8:item>
			</Synonym>
			<Comment>Общие рабочие поручения и персональные задания</Comment>
			<UseStandardCommands>false</UseStandardCommands>
			<NumberType>String</NumberType>
			<NumberLength>0</NumberLength>
			<NumberAllowedLength>Fixed</NumberAllowedLength>
			<CheckUnique>true</CheckUnique>
			<Autonumbering>true</Autonumbering>
			<TaskNumberAutoPrefix>DontUse</TaskNumberAutoPrefix>
			<DescriptionLength>100</DescriptionLength>
			<Addressing>InformationRegister.Адресация</Addressing>
			<MainAddressingAttribute>Task.ЗадачиПользователя.AddressingAttribute.Исполнитель</MainAddressingAttribute>
			<CurrentPerformer>SessionParameter.ТекущийПользователь</CurrentPerformer>
			<BasedOn/>
			<StandardAttributes>
				<xr:StandardAttribute name="Executed">
					<xr:LinkByType/>
					<xr:FillChecking>DontCheck</xr:FillChecking>
					<xr:MultiLine>false</xr:MultiLine>
					<xr:FillFromFillingValue>false</xr:FillFromFillingValue>
					<xr:CreateOnInput>Auto</xr:CreateOnInput>
					<xr:MaxValue xsi:nil="true"/>
					<xr:ToolTip/>
					<xr:ExtendedEdit>false</xr:ExtendedEdit>
					<xr:Format/>
					<xr:ChoiceForm/>
					<xr:QuickChoice>Auto</xr:QuickChoice>
					<xr:ChoiceHistoryOnInput>Auto</xr:ChoiceHistoryOnInput>
					<xr:EditFormat/>
					<xr:PasswordMode>false</xr:PasswordMode>
					<xr:MarkNegatives>false</xr:MarkNegatives>
					<xr:MinValue xsi:nil="true"/>
					<xr:Synonym/>
					<xr:Comment/>
					<xr:FullTextSearch>Use</xr:FullTextSearch>
					<xr:ChoiceParameterLinks/>
					<xr:FillValue xsi:nil="true"/>
					<xr:Mask/>
					<xr:ChoiceParameters/>
				</xr:StandardAttribute>
				<xr:StandardAttribute name="Description">
					<xr:LinkByType/>
					<xr:FillChecking>ShowError</xr:FillChecking>
					<xr:MultiLine>false</xr:MultiLine>
					<xr:FillFromFillingValue>false</xr:FillFromFillingValue>
					<xr:CreateOnInput>Auto</xr:CreateOnInput>
					<xr:MaxValue xsi:nil="true"/>
					<xr:ToolTip/>
					<xr:ExtendedEdit>false</xr:ExtendedEdit>
					<xr:Format/>
					<xr:ChoiceForm/>
					<xr:QuickChoice>Auto</xr:QuickChoice>
					<xr:ChoiceHistoryOnInput>Auto</xr:ChoiceHistoryOnInput>
					<xr:EditFormat/>
					<xr:PasswordMode>false</xr:PasswordMode>
					<xr:MarkNegatives>false</xr:MarkNegatives>
					<xr:MinValue xsi:nil="true"/>
					<xr:Synonym/>
					<xr:Comment/>
					<xr:FullTextSearch>Use</xr:FullTextSearch>
					<xr:ChoiceParameterLinks/>
					<xr:FillValue xsi:nil="true"/>
					<xr:Mask/>
					<xr:ChoiceParameters/>
				</xr:StandardAttribute>
				<xr:StandardAttribute name="RoutePoint">
					<xr:LinkByType/>
					<xr:FillChecking>DontCheck</xr:FillChecking>
					<xr:MultiLine>false</xr:MultiLine>
					<xr:FillFromFillingValue>false</xr:FillFromFillingValue>
					<xr:CreateOnInput>Auto</xr:CreateOnInput>
					<xr:MaxValue xsi:nil="true"/>
					<xr:ToolTip/>
					<xr:ExtendedEdit>false</xr:ExtendedEdit>
					<xr:Format/>
					<xr:ChoiceForm/>
					<xr:QuickChoice>Auto</xr:QuickChoice>
					<xr:ChoiceHistoryOnInput>Auto</xr:ChoiceHistoryOnInput>
					<xr:EditFormat/>
					<xr:PasswordMode>false</xr:PasswordMode>
					<xr:MarkNegatives>false</xr:MarkNegatives>
					<xr:MinValue xsi:nil="true"/>
					<xr:Synonym/>
					<xr:Comment/>
					<xr:FullTextSearch>Use</xr:FullTextSearch>
					<xr:ChoiceParameterLinks/>
					<xr:FillValue xsi:nil="true"/>
					<xr:Mask/>
					<xr:ChoiceParameters/>
				</xr:StandardAttribute>
				<xr:StandardAttribute name="BusinessProcess">
					<xr:LinkByType/>
					<xr:FillChecking>DontCheck</xr:FillChecking>
					<xr:MultiLine>false</xr:MultiLine>
					<xr:FillFromFillingValue>false</xr:FillFromFillingValue>
					<xr:CreateOnInput>Auto</xr:CreateOnInput>
					<xr:MaxValue xsi:nil="true"/>
					<xr:ToolTip/>
					<xr:ExtendedEdit>false</xr:ExtendedEdit>
					<xr:Format/>
					<xr:ChoiceForm/>
					<xr:QuickChoice>Auto</xr:QuickChoice>
					<xr:ChoiceHistoryOnInput>Auto</xr:ChoiceHistoryOnInput>
					<xr:EditFormat/>
					<xr:PasswordMode>false</xr:PasswordMode>
					<xr:MarkNegatives>false</xr:MarkNegatives>
					<xr:MinValue xsi:nil="true"/>
					<xr:Synonym/>
					<xr:Comment/>
					<xr:FullTextSearch>Use</xr:FullTextSearch>
					<xr:ChoiceParameterLinks/>
					<xr:FillValue xsi:nil="true"/>
					<xr:Mask/>
					<xr:ChoiceParameters/>
				</xr:StandardAttribute>
				<xr:StandardAttribute name="Ref">
					<xr:LinkByType/>
					<xr:FillChecking>DontCheck</xr:FillChecking>
					<xr:MultiLine>false</xr:MultiLine>
					<xr:FillFromFillingValue>false</xr:FillFromFillingValue>
					<xr:CreateOnInput>Auto</xr:CreateOnInput>
					<xr:MaxValue xsi:nil="true"/>
					<xr:ToolTip/>
					<xr:ExtendedEdit>false</xr:ExtendedEdit>
					<xr:Format/>
					<xr:ChoiceForm/>
					<xr:QuickChoice>Auto</xr:QuickChoice>
					<xr:ChoiceHistoryOnInput>Auto</xr:ChoiceHistoryOnInput>
					<xr:EditFormat/>
					<xr:PasswordMode>false</xr:PasswordMode>
					<xr:MarkNegatives>false</xr:MarkNegatives>
					<xr:MinValue xsi:nil="true"/>
					<xr:Synonym/>
					<xr:Comment/>
					<xr:FullTextSearch>Use</xr:FullTextSearch>
					<xr:ChoiceParameterLinks/>
					<xr:FillValue xsi:nil="true"/>
					<xr:Mask/>
					<xr:ChoiceParameters/>
				</xr:StandardAttribute>
				<xr:StandardAttribute name="DeletionMark">
					<xr:LinkByType/>
					<xr:FillChecking>DontCheck</xr:FillChecking>
					<xr:MultiLine>false</xr:MultiLine>
					<xr:FillFromFillingValue>false</xr:FillFromFillingValue>
					<xr:CreateOnInput>Auto</xr:CreateOnInput>
					<xr:MaxValue xsi:nil="true"/>
					<xr:ToolTip/>
					<xr:ExtendedEdit>false</xr:ExtendedEdit>
					<xr:Format/>
					<xr:ChoiceForm/>
					<xr:QuickChoice>Auto</xr:QuickChoice>
					<xr:ChoiceHistoryOnInput>Auto</xr:ChoiceHistoryOnInput>
					<xr:EditFormat/>
					<xr:PasswordMode>false</xr:PasswordMode>
					<xr:MarkNegatives>false</xr:MarkNegatives>
					<xr:MinValue xsi:nil="true"/>
					<xr:Synonym/>
					<xr:Comment/>
					<xr:FullTextSearch>Use</xr:FullTextSearch>
					<xr:ChoiceParameterLinks/>
					<xr:FillValue xsi:nil="true"/>
					<xr:Mask/>
					<xr:ChoiceParameters/>
				</xr:StandardAttribute>
				<xr:StandardAttribute name="Date">
					<xr:LinkByType/>
					<xr:FillChecking>DontCheck</xr:FillChecking>
					<xr:MultiLine>false</xr:MultiLine>
					<xr:FillFromFillingValue>false</xr:FillFromFillingValue>
					<xr:CreateOnInput>Auto</xr:CreateOnInput>
					<xr:MaxValue xsi:nil="true"/>
					<xr:ToolTip/>
					<xr:ExtendedEdit>false</xr:ExtendedEdit>
					<xr:Format/>
					<xr:ChoiceForm/>
					<xr:QuickChoice>Auto</xr:QuickChoice>
					<xr:ChoiceHistoryOnInput>Auto</xr:ChoiceHistoryOnInput>
					<xr:EditFormat/>
					<xr:PasswordMode>false</xr:PasswordMode>
					<xr:MarkNegatives>false</xr:MarkNegatives>
					<xr:MinValue xsi:nil="true"/>
					<xr:Synonym/>
					<xr:Comment/>
					<xr:FullTextSearch>Use</xr:FullTextSearch>
					<xr:ChoiceParameterLinks/>
					<xr:FillValue xsi:nil="true"/>
					<xr:Mask/>
					<xr:ChoiceParameters/>
				</xr:StandardAttribute>
				<xr:StandardAttribute name="Number">
					<xr:LinkByType/>
					<xr:FillChecking>DontCheck</xr:FillChecking>
					<xr:MultiLine>false</xr:MultiLine>
					<xr:FillFromFillingValue>false</xr:FillFromFillingValue>
					<xr:CreateOnInput>Auto</xr:CreateOnInput>
					<xr:MaxValue xsi:nil="true"/>
					<xr:ToolTip/>
					<xr:ExtendedEdit>false</xr:ExtendedEdit>
					<xr:Format/>
					<xr:ChoiceForm/>
					<xr:QuickChoice>Auto</xr:QuickChoice>
					<xr:ChoiceHistoryOnInput>Auto</xr:ChoiceHistoryOnInput>
					<xr:EditFormat/>
					<xr:PasswordMode>false</xr:PasswordMode>
					<xr:MarkNegatives>false</xr:MarkNegatives>
					<xr:MinValue xsi:nil="true"/>
					<xr:Synonym/>
					<xr:Comment/>
					<xr:FullTextSearch>Use</xr:FullTextSearch>
					<xr:ChoiceParameterLinks/>
					<xr:FillValue xsi:nil="true"/>
					<xr:Mask/>
					<xr:ChoiceParameters/>
				</xr:StandardAttribute>
			</StandardAttributes>
			<Characteristics/>
			<DefaultPresentation>AsDescription</DefaultPresentation>
			<EditType>InDialog</EditType>
			<InputByString>
				<xr:Field>Task.ЗадачиПользователя.StandardAttribute.Description</xr:Field>
			</InputByString>
			<SearchStringModeOnInputByString>Begin</SearchStringModeOnInputByString>
			<FullTextSearchOnInputByString>DontUse</FullTextSearchOnInputByString>
			<ChoiceDataGetModeOnInputByString>Directly</ChoiceDataGetModeOnInputByString>
			<CreateOnInput>DontUse</CreateOnInput>
			<DefaultObjectForm>Task.ЗадачиПользователя.Form.ФормаЗадачи</DefaultObjectForm>
			<DefaultListForm>Task.ЗадачиПользователя.Form.ФормаСписка</DefaultListForm>
			<DefaultChoiceForm/>
			<AuxiliaryObjectForm/>
			<AuxiliaryListForm/>
			<AuxiliaryChoiceForm/>
			<ChoiceHistoryOnInput>Auto</ChoiceHistoryOnInput>
			<IncludeHelpInContents>true</IncludeHelpInContents>
			<DataLockFields/>
			<DataLockControlMode>Automatic</DataLockControlMode>
			<FullTextSearch>DontUse</FullTextSearch>
			<ObjectPresentation/>
			<ExtendedObjectPresentation/>
			<ListPresentation/>
			<ExtendedListPresentation/>
			<Explanation/>
		</Properties>
		<ChildObjects>
			<Attribute uuid="010e65fc-8c61-422d-bcec-0b43324e8411">
				<Properties>
					<Name>СрокИсполнения</Name>
					<Synonym>
						<v8:item>
							<v8:lang>ru</v8:lang>
							<v8:content>Срок исполнения</v8:content>
						</v8:item>
					</Synonym>
					<Comment/>
					<Type>
						<v8:Type>xs:dateTime</v8:Type>
						<v8:DateQualifiers>
							<v8:DateFractions>DateTime</v8:DateFractions>
						</v8:DateQualifiers>
					</Type>
					<PasswordMode>false</PasswordMode>
					<Format/>
					<EditFormat/>
					<ToolTip/>
					<MarkNegatives>false</MarkNegatives>
					<Mask/>
					<MultiLine>false</MultiLine>
					<ExtendedEdit>false</ExtendedEdit>
					<MinValue xsi:nil="true"/>
					<MaxValue xsi:nil="true"/>
					<FillFromFillingValue>false</FillFromFillingValue>
					<FillValue xsi:nil="true"/>
					<FillChecking>DontCheck</FillChecking>
					<ChoiceFoldersAndItems>Items</ChoiceFoldersAndItems>
					<ChoiceParameterLinks/>
					<ChoiceParameters/>
					<QuickChoice>Auto</QuickChoice>
					<CreateOnInput>Auto</CreateOnInput>
					<ChoiceForm/>
					<LinkByType/>
					<ChoiceHistoryOnInput>Auto</ChoiceHistoryOnInput>
					<Indexing>Index</Indexing>
					<FullTextSearch>DontUse</FullTextSearch>
				</Properties>
			</Attribute>
			<Attribute uuid="17487418-0159-430f-affd-ee71c8becaff">
				<Properties>
					<Name>Описание</Name>
					<Synonym>
						<v8:item>
							<v8:lang>ru</v8:lang>
							<v8:content>Описание</v8:content>
						</v8:item>
					</Synonym>
					<Comment/>
					<Type>
						<v8:Type>xs:string</v8:Type>
						<v8:StringQualifiers>
							<v8:Length>0</v8:Length>
							<v8:AllowedLength>Variable</v8:AllowedLength>
						</v8:StringQualifiers>
					</Type>
					<PasswordMode>false</PasswordMode>
					<Format/>
					<EditFormat/>
					<ToolTip/>
					<MarkNegatives>false</MarkNegatives>
					<Mask/>
					<MultiLine>false</MultiLine>
					<ExtendedEdit>false</ExtendedEdit>
					<MinValue xsi:nil="true"/>
					<MaxValue xsi:nil="true"/>
					<FillFromFillingValue>false</FillFromFillingValue>
					<FillValue xsi:nil="true"/>
					<FillChecking>DontCheck</FillChecking>
					<ChoiceFoldersAndItems>Items</ChoiceFoldersAndItems>
					<ChoiceParameterLinks/>
					<ChoiceParameters/>
					<QuickChoice>Auto</QuickChoice>
					<CreateOnInput>Auto</CreateOnInput>
					<ChoiceForm/>
					<LinkByType/>
					<ChoiceHistoryOnInput>Auto</ChoiceHistoryOnInput>
					<Indexing>DontIndex</Indexing>
					<FullTextSearch>DontUse</FullTextSearch>
				</Properties>
			</Attribute>
			<Attribute uuid="5014257c-f387-44bd-b336-35e5e79abbf0">
				<Properties>
					<Name>Объект</Name>
					<Synonym>
						<v8:item>
							<v8:lang>ru</v8:lang>
							<v8:content>Объект</v8:content>
						</v8:item>
					</Synonym>
					<Comment/>
					<Type>
						<v8:Type>cfg:CatalogRef.Контрагенты</v8:Type>
						<v8:Type>cfg:CatalogRef.Пользователи</v8:Type>
						<v8:Type>cfg:CatalogRef.КонтактныеЛица</v8:Type>
						<v8:Type>cfg:CatalogRef.ДоговорыКонтрагентов</v8:Type>
					</Type>
					<PasswordMode>false</PasswordMode>
					<Format/>
					<EditFormat/>
					<ToolTip/>
					<MarkNegatives>false</MarkNegatives>
					<Mask/>
					<MultiLine>false</MultiLine>
					<ExtendedEdit>false</ExtendedEdit>
					<MinValue xsi:nil="true"/>
					<MaxValue xsi:nil="true"/>
					<FillFromFillingValue>false</FillFromFillingValue>
					<FillValue xsi:nil="true"/>
					<FillChecking>DontCheck</FillChecking>
					<ChoiceFoldersAndItems>Items</ChoiceFoldersAndItems>
					<ChoiceParameterLinks/>
					<ChoiceParameters/>
					<QuickChoice>Auto</QuickChoice>
					<CreateOnInput>Auto</CreateOnInput>
					<ChoiceForm/>
					<LinkByType/>
					<ChoiceHistoryOnInput>Auto</ChoiceHistoryOnInput>
					<Indexing>Index</Indexing>
					<FullTextSearch>DontUse</FullTextSearch>
				</Properties>
			</Attribute>
			<Attribute uuid="73987151-37dd-4f4b-a1a9-92233ac6b3bc">
				<Properties>
					<Name>Инициатор</Name>
					<Synonym>
						<v8:item>
							<v8:lang>ru</v8:lang>
							<v8:content>Инициатор</v8:content>
						</v8:item>
					</Synonym>
					<Comment/>
					<Type>
						<v8:Type>cfg:CatalogRef.Пользователи</v8:Type>
					</Type>
					<PasswordMode>false</PasswordMode>
					<Format/>
					<EditFormat/>
					<ToolTip/>
					<MarkNegatives>false</MarkNegatives>
					<Mask/>
					<MultiLine>false</MultiLine>
					<ExtendedEdit>false</ExtendedEdit>
					<MinValue xsi:nil="true"/>
					<MaxValue xsi:nil="true"/>
					<FillFromFillingValue>false</FillFromFillingValue>
					<FillValue xsi:nil="true"/>
					<FillChecking>DontCheck</FillChecking>
					<ChoiceFoldersAndItems>Items</ChoiceFoldersAndItems>
					<ChoiceParameterLinks/>
					<ChoiceParameters/>
					<QuickChoice>Auto</QuickChoice>
					<CreateOnInput>Auto</CreateOnInput>
					<ChoiceForm/>
					<LinkByType/>
					<ChoiceHistoryOnInput>Auto</ChoiceHistoryOnInput>
					<Indexing>DontIndex</Indexing>
					<FullTextSearch>DontUse</FullTextSearch>
				</Properties>
			</Attribute>
			<Attribute uuid="5a80b5fc-f0fe-4a89-833a-57077b2edf99">
				<Properties>
					<Name>Оповещение</Name>
					<Synonym>
						<v8:item>
							<v8:lang>ru</v8:lang>
							<v8:content>Оповещение</v8:content>
						</v8:item>
					</Synonym>
					<Comment/>
					<Type>
						<v8:Type>xs:boolean</v8:Type>
					</Type>
					<PasswordMode>false</PasswordMode>
					<Format/>
					<EditFormat/>
					<ToolTip/>
					<MarkNegatives>false</MarkNegatives>
					<Mask/>
					<MultiLine>false</MultiLine>
					<ExtendedEdit>false</ExtendedEdit>
					<MinValue xsi:nil="true"/>
					<MaxValue xsi:nil="true"/>
					<FillFromFillingValue>false</FillFromFillingValue>
					<FillValue xsi:nil="true"/>
					<FillChecking>DontCheck</FillChecking>
					<ChoiceFoldersAndItems>Items</ChoiceFoldersAndItems>
					<ChoiceParameterLinks/>
					<ChoiceParameters/>
					<QuickChoice>Auto</QuickChoice>
					<CreateOnInput>Auto</CreateOnInput>
					<ChoiceForm/>
					<LinkByType/>
					<ChoiceHistoryOnInput>Auto</ChoiceHistoryOnInput>
					<Indexing>Index</Indexing>
					<FullTextSearch>DontUse</FullTextSearch>
				</Properties>
			</Attribute>
			<Attribute uuid="847d6a80-25bf-49d7-a1c2-2a670588d771">
				<Properties>
					<Name>СрокОповещения</Name>
					<Synonym>
						<v8:item>
							<v8:lang>ru</v8:lang>
							<v8:content>Срок оповещения</v8:content>
						</v8:item>
					</Synonym>
					<Comment/>
					<Type>
						<v8:Type>xs:dateTime</v8:Type>
						<v8:DateQualifiers>
							<v8:DateFractions>DateTime</v8:DateFractions>
						</v8:DateQualifiers>
					</Type>
					<PasswordMode>false</PasswordMode>
					<Format/>
					<EditFormat/>
					<ToolTip/>
					<MarkNegatives>false</MarkNegatives>
					<Mask/>
					<MultiLine>false</MultiLine>
					<ExtendedEdit>false</ExtendedEdit>
					<MinValue xsi:nil="true"/>
					<MaxValue xsi:nil="true"/>
					<FillFromFillingValue>false</FillFromFillingValue>
					<FillValue xsi:nil="true"/>
					<FillChecking>DontCheck</FillChecking>
					<ChoiceFoldersAndItems>Items</ChoiceFoldersAndItems>
					<ChoiceParameterLinks/>
					<ChoiceParameters/>
					<QuickChoice>Auto</QuickChoice>
					<CreateOnInput>Auto</CreateOnInput>
					<ChoiceForm/>
					<LinkByType/>
					<ChoiceHistoryOnInput>Auto</ChoiceHistoryOnInput>
					<Indexing>Index</Indexing>
					<FullTextSearch>DontUse</FullTextSearch>
				</Properties>
			</Attribute>
			<Attribute uuid="90f302de-ad06-414b-8b0a-dc17fff9c66a">
				<Properties>
					<Name>ПамятнаяДата</Name>
					<Synonym>
						<v8:item>
							<v8:lang>ru</v8:lang>
							<v8:content>Памятная дата</v8:content>
						</v8:item>
					</Synonym>
					<Comment/>
					<Type>
						<v8:Type>xs:boolean</v8:Type>
					</Type>
					<PasswordMode>false</PasswordMode>
					<Format/>
					<EditFormat/>
					<ToolTip/>
					<MarkNegatives>false</MarkNegatives>
					<Mask/>
					<MultiLine>false</MultiLine>
					<ExtendedEdit>false</ExtendedEdit>
					<MinValue xsi:nil="true"/>
					<MaxValue xsi:nil="true"/>
					<FillFromFillingValue>false</FillFromFillingValue>
					<FillValue xsi:nil="true"/>
					<FillChecking>DontCheck</FillChecking>
					<ChoiceFoldersAndItems>Items</ChoiceFoldersAndItems>
					<ChoiceParameterLinks/>
					<ChoiceParameters/>
					<QuickChoice>Auto</QuickChoice>
					<CreateOnInput>Auto</CreateOnInput>
					<ChoiceForm/>
					<LinkByType/>
					<ChoiceHistoryOnInput>Auto</ChoiceHistoryOnInput>
					<Indexing>Index</Indexing>
					<FullTextSearch>DontUse</FullTextSearch>
				</Properties>
			</Attribute>
			<Attribute uuid="d7a94f91-3e9e-46eb-9b16-051d83077f9b">
				<Properties>
					<Name>ДатаИсполнения</Name>
					<Synonym>
						<v8:item>
							<v8:lang>ru</v8:lang>
							<v8:content>Дата исполнения</v8:content>
						</v8:item>
					</Synonym>
					<Comment>Дата выполнения задачи</Comment>
					<Type>
						<v8:Type>xs:dateTime</v8:Type>
						<v8:DateQualifiers>
							<v8:DateFractions>DateTime</v8:DateFractions>
						</v8:DateQualifiers>
					</Type>
					<PasswordMode>false</PasswordMode>
					<Format/>
					<EditFormat/>
					<ToolTip/>
					<MarkNegatives>false</MarkNegatives>
					<Mask/>
					<MultiLine>false</MultiLine>
					<ExtendedEdit>false</ExtendedEdit>
					<MinValue xsi:nil="true"/>
					<MaxValue xsi:nil="true"/>
					<FillFromFillingValue>false</FillFromFillingValue>
					<FillValue xsi:nil="true"/>
					<FillChecking>DontCheck</FillChecking>
					<ChoiceFoldersAndItems>Items</ChoiceFoldersAndItems>
					<ChoiceParameterLinks/>
					<ChoiceParameters/>
					<QuickChoice>Auto</QuickChoice>
					<CreateOnInput>Auto</CreateOnInput>
					<ChoiceForm/>
					<LinkByType/>
					<ChoiceHistoryOnInput>Auto</ChoiceHistoryOnInput>
					<Indexing>DontIndex</Indexing>
					<FullTextSearch>DontUse</FullTextSearch>
				</Properties>
			</Attribute>
			<Form>РабочаяФормаСпискаЗадачПользователя</Form>
			<Form>ФормаЗадачи</Form>
			<Form>ФормаОповещенияОЗадачах</Form>
			<Form>ФормаСписка</Form>
			<Form>ПереоценкаТоваровАТТВыполнениеЗадачи</Form>
			<Form>ПереоценкаТоваровРозницаВыполнениеЗадачи</Form>
			<Form>СогласованиеЗаказаПокупателяВыполнениеЗадачи</Form>
			<Form>ФормаРаботыСКонтрагентом</Form>
			<Form>ФормаЗаявкиНаДобавлениеПользователя</Form>
			<AddressingAttribute uuid="518cad9e-2aa9-4f29-bff1-399950ba93b3">
				<Properties>
					<Name>Исполнитель</Name>
					<Synonym>
						<v8:item>
							<v8:lang>ru</v8:lang>
							<v8:content>Исполнитель</v8:content>
						</v8:item>
					</Synonym>
					<Comment/>
					<Type>
						<v8:Type>cfg:CatalogRef.Пользователи</v8:Type>
					</Type>
					<PasswordMode>false</PasswordMode>
					<Format/>
					<EditFormat/>
					<ToolTip/>
					<MarkNegatives>false</MarkNegatives>
					<Mask/>
					<MultiLine>false</MultiLine>
					<ExtendedEdit>false</ExtendedEdit>
					<MinValue xsi:nil="true"/>
					<MaxValue xsi:nil="true"/>
					<FillFromFillingValue>false</FillFromFillingValue>
					<FillValue xsi:nil="true"/>
					<FillChecking>DontCheck</FillChecking>
					<ChoiceFoldersAndItems>Items</ChoiceFoldersAndItems>
					<ChoiceParameterLinks/>
					<ChoiceParameters/>
					<QuickChoice>Auto</QuickChoice>
					<CreateOnInput>Auto</CreateOnInput>
					<ChoiceForm/>
					<LinkByType/>
					<ChoiceHistoryOnInput>Auto</ChoiceHistoryOnInput>
					<Indexing>DontIndex</Indexing>
					<AddressingDimension>InformationRegister.Адресация.Dimension.Исполнитель</AddressingDimension>
					<FullTextSearch>DontUse</FullTextSearch>
				</Properties>
			</AddressingAttribute>
			<AddressingAttribute uuid="4652ea17-e7a5-42f5-8e8e-51e62edad59b">
				<Properties>
					<Name>Должность</Name>
					<Synonym>
						<v8:item>
							<v8:lang>ru</v8:lang>
							<v8:content>Должность</v8:content>
						</v8:item>
					</Synonym>
					<Comment/>
					<Type>
						<v8:Type>cfg:CatalogRef.ДолжностиОрганизаций</v8:Type>
					</Type>
					<PasswordMode>false</PasswordMode>
					<Format/>
					<EditFormat/>
					<ToolTip/>
					<MarkNegatives>false</MarkNegatives>
					<Mask/>
					<MultiLine>false</MultiLine>
					<ExtendedEdit>false</ExtendedEdit>
					<MinValue xsi:nil="true"/>
					<MaxValue xsi:nil="true"/>
					<FillFromFillingValue>false</FillFromFillingValue>
					<FillValue xsi:nil="true"/>
					<FillChecking>DontCheck</FillChecking>
					<ChoiceFoldersAndItems>Items</ChoiceFoldersAndItems>
					<ChoiceParameterLinks/>
					<ChoiceParameters/>
					<QuickChoice>Auto</QuickChoice>
					<CreateOnInput>Auto</CreateOnInput>
					<ChoiceForm/>
					<LinkByType/>
					<ChoiceHistoryOnInput>Auto</ChoiceHistoryOnInput>
					<Indexing>DontIndex</Indexing>
					<AddressingDimension>InformationRegister.Адресация.Dimension.Должность</AddressingDimension>
					<FullTextSearch>DontUse</FullTextSearch>
				</Properties>
			</AddressingAttribute>
		</ChildObjects>
	</Task>
</MetaDataObject>