<?xml version="1.0" encoding="UTF-8"?>
<MetaDataObject xmlns="http://v8.1c.ru/8.3/MDClasses" xmlns:app="http://v8.1c.ru/8.2/managed-application/core" xmlns:cfg="http://v8.1c.ru/8.1/data/enterprise/current-config" xmlns:cmi="http://v8.1c.ru/8.2/managed-application/cmi" xmlns:ent="http://v8.1c.ru/8.1/data/enterprise" xmlns:lf="http://v8.1c.ru/8.2/managed-application/logform" xmlns:style="http://v8.1c.ru/8.1/data/ui/style" xmlns:sys="http://v8.1c.ru/8.1/data/ui/fonts/system" xmlns:v8="http://v8.1c.ru/8.1/data/core" xmlns:v8ui="http://v8.1c.ru/8.1/data/ui" xmlns:web="http://v8.1c.ru/8.1/data/ui/colors/web" xmlns:win="http://v8.1c.ru/8.1/data/ui/colors/windows" xmlns:xen="http://v8.1c.ru/8.3/xcf/enums" xmlns:xpr="http://v8.1c.ru/8.3/xcf/predef" xmlns:xr="http://v8.1c.ru/8.3/xcf/readable" xmlns:xs="http://www.w3.org/2001/XMLSchema" xmlns:xsi="http://www.w3.org/2001/XMLSchema-instance" version="2.4">
	<ExchangePlan uuid="46d73889-585a-4451-8e60-d6b73029e5d7">
		<InternalInfo>
			<xr:ThisNode>0fdc0e30-57ea-4a2c-8cb5-cd1d5e66d5f8</xr:ThisNode>
			<xr:GeneratedType name="ExchangePlanObject.ОбменПартКом83_Сайт_Возвраты" category="Object">
				<xr:TypeId>e0616b49-d55e-4697-9730-b107d69d06a3</xr:TypeId>
				<xr:ValueId>8a3cfbdc-de45-4dec-9a11-344cee2bd427</xr:ValueId>
			</xr:GeneratedType>
			<xr:GeneratedType name="ExchangePlanRef.ОбменПартКом83_Сайт_Возвраты" category="Ref">
				<xr:TypeId>bc48fa03-5840-4712-9286-39c8980a8241</xr:TypeId>
				<xr:ValueId>99ceac0a-1630-45d6-9433-00874766b995</xr:ValueId>
			</xr:GeneratedType>
			<xr:GeneratedType name="ExchangePlanSelection.ОбменПартКом83_Сайт_Возвраты" category="Selection">
				<xr:TypeId>fe2297dd-38be-47a8-a49f-f52cf706af67</xr:TypeId>
				<xr:ValueId>d81fb894-f7a5-44c8-bcd0-6ca8179e6678</xr:ValueId>
			</xr:GeneratedType>
			<xr:GeneratedType name="ExchangePlanList.ОбменПартКом83_Сайт_Возвраты" category="List">
				<xr:TypeId>cb819cdb-4574-48d9-939e-27f3955c1bf1</xr:TypeId>
				<xr:ValueId>cf06cc2b-451e-455c-ba9b-195b88cf639b</xr:ValueId>
			</xr:GeneratedType>
			<xr:GeneratedType name="ExchangePlanManager.ОбменПартКом83_Сайт_Возвраты" category="Manager">
				<xr:TypeId>cf71f8e8-84a6-444e-b200-e5aa0b3a4fd2</xr:TypeId>
				<xr:ValueId>7123304a-1c5d-43ae-bfa3-5f0c2cd4aee7</xr:ValueId>
			</xr:GeneratedType>
		</InternalInfo>
		<Properties>
			<Name>ОбменПартКом83_Сайт_Возвраты</Name>
			<Synonym>
				<v8:item>
					<v8:lang>ru</v8:lang>
					<v8:content>Обмен парт ком83 сайт возвраты</v8:content>
				</v8:item>
			</Synonym>
			<Comment/>
			<UseStandardCommands>false</UseStandardCommands>
			<CodeLength>9</CodeLength>
			<CodeAllowedLength>Variable</CodeAllowedLength>
			<DescriptionLength>25</DescriptionLength>
			<DefaultPresentation>AsDescription</DefaultPresentation>
			<EditType>InDialog</EditType>
			<QuickChoice>false</QuickChoice>
			<ChoiceMode>BothWays</ChoiceMode>
			<InputByString>
				<xr:Field>ExchangePlan.ОбменПартКом83_Сайт_Возвраты.StandardAttribute.Description</xr:Field>
				<xr:Field>ExchangePlan.ОбменПартКом83_Сайт_Возвраты.StandardAttribute.Code</xr:Field>
			</InputByString>
			<SearchStringModeOnInputByString>Begin</SearchStringModeOnInputByString>
			<FullTextSearchOnInputByString>DontUse</FullTextSearchOnInputByString>
			<ChoiceDataGetModeOnInputByString>Directly</ChoiceDataGetModeOnInputByString>
			<DefaultObjectForm/>
			<DefaultListForm/>
			<DefaultChoiceForm/>
			<AuxiliaryObjectForm/>
			<AuxiliaryListForm/>
			<AuxiliaryChoiceForm/>
			<Characteristics/>
			<BasedOn/>
			<DistributedInfoBase>false</DistributedInfoBase>
			<CreateOnInput>DontUse</CreateOnInput>
			<ChoiceHistoryOnInput>Auto</ChoiceHistoryOnInput>
			<IncludeHelpInContents>false</IncludeHelpInContents>
			<DataLockFields/>
			<DataLockControlMode>Managed</DataLockControlMode>
			<FullTextSearch>Use</FullTextSearch>
			<ObjectPresentation/>
			<ExtendedObjectPresentation/>
			<ListPresentation/>
			<ExtendedListPresentation/>
			<Explanation/>
		</Properties>
		<ChildObjects>
			<Attribute uuid="64860010-faf8-4c54-a118-038b046e3291">
				<Properties>
					<Name>ИдентификаторУзла</Name>
					<Synonym>
						<v8:item>
							<v8:lang>ru</v8:lang>
							<v8:content>Идентификатор узла</v8:content>
						</v8:item>
					</Synonym>
					<Comment/>
					<Type>
						<v8:Type>xs:decimal</v8:Type>
						<v8:NumberQualifiers>
							<v8:Digits>3</v8:Digits>
							<v8:FractionDigits>0</v8:FractionDigits>
							<v8:AllowedSign>Nonnegative</v8:AllowedSign>
						</v8:NumberQualifiers>
					</Type>
					<PasswordMode>false</PasswordMode>
					<Format/>
					<EditFormat/>
					<ToolTip/>
					<MarkNegatives>false</MarkNegatives>
					<Mask/>
					<MultiLine>false</MultiLine>
					<ExtendedEdit>false</ExtendedEdit>
					<MinValue xsi:nil="true"/>
					<MaxValue xsi:nil="true"/>
					<FillFromFillingValue>false</FillFromFillingValue>
					<FillValue xsi:nil="true"/>
					<FillChecking>DontCheck</FillChecking>
					<ChoiceFoldersAndItems>Items</ChoiceFoldersAndItems>
					<ChoiceParameterLinks/>
					<ChoiceParameters/>
					<QuickChoice>Auto</QuickChoice>
					<CreateOnInput>Auto</CreateOnInput>
					<ChoiceForm/>
					<LinkByType/>
					<ChoiceHistoryOnInput>Auto</ChoiceHistoryOnInput>
					<Indexing>DontIndex</Indexing>
					<FullTextSearch>Use</FullTextSearch>
				</Properties>
			</Attribute>
			<Attribute uuid="39b47a50-4d60-4cae-a296-6caafda7ad31">
				<Properties>
					<Name>Входящий</Name>
					<Synonym>
						<v8:item>
							<v8:lang>ru</v8:lang>
							<v8:content>Входящий</v8:content>
						</v8:item>
					</Synonym>
					<Comment/>
					<Type>
						<v8:Type>xs:boolean</v8:Type>
					</Type>
					<PasswordMode>false</PasswordMode>
					<Format/>
					<EditFormat/>
					<ToolTip/>
					<MarkNegatives>false</MarkNegatives>
					<Mask/>
					<MultiLine>false</MultiLine>
					<ExtendedEdit>false</ExtendedEdit>
					<MinValue xsi:nil="true"/>
					<MaxValue xsi:nil="true"/>
					<FillFromFillingValue>false</FillFromFillingValue>
					<FillValue xsi:nil="true"/>
					<FillChecking>DontCheck</FillChecking>
					<ChoiceFoldersAndItems>Items</ChoiceFoldersAndItems>
					<ChoiceParameterLinks/>
					<ChoiceParameters/>
					<QuickChoice>Auto</QuickChoice>
					<CreateOnInput>Auto</CreateOnInput>
					<ChoiceForm/>
					<LinkByType/>
					<ChoiceHistoryOnInput>Auto</ChoiceHistoryOnInput>
					<Indexing>DontIndex</Indexing>
					<FullTextSearch>Use</FullTextSearch>
				</Properties>
			</Attribute>
			<Attribute uuid="5705fc29-056c-4690-aadb-b273614dd02f">
				<Properties>
					<Name>Исходящий</Name>
					<Synonym>
						<v8:item>
							<v8:lang>ru</v8:lang>
							<v8:content>Исходящий</v8:content>
						</v8:item>
					</Synonym>
					<Comment/>
					<Type>
						<v8:Type>xs:boolean</v8:Type>
					</Type>
					<PasswordMode>false</PasswordMode>
					<Format/>
					<EditFormat/>
					<ToolTip/>
					<MarkNegatives>false</MarkNegatives>
					<Mask/>
					<MultiLine>false</MultiLine>
					<ExtendedEdit>false</ExtendedEdit>
					<MinValue xsi:nil="true"/>
					<MaxValue xsi:nil="true"/>
					<FillFromFillingValue>false</FillFromFillingValue>
					<FillValue xsi:nil="true"/>
					<FillChecking>DontCheck</FillChecking>
					<ChoiceFoldersAndItems>Items</ChoiceFoldersAndItems>
					<ChoiceParameterLinks/>
					<ChoiceParameters/>
					<QuickChoice>Auto</QuickChoice>
					<CreateOnInput>Auto</CreateOnInput>
					<ChoiceForm/>
					<LinkByType/>
					<ChoiceHistoryOnInput>Auto</ChoiceHistoryOnInput>
					<Indexing>DontIndex</Indexing>
					<FullTextSearch>Use</FullTextSearch>
				</Properties>
			</Attribute>
		</ChildObjects>
	</ExchangePlan>
</MetaDataObject>