<?xml version="1.0" encoding="UTF-8"?>
<MetaDataObject xmlns="http://v8.1c.ru/8.3/MDClasses" xmlns:app="http://v8.1c.ru/8.2/managed-application/core" xmlns:cfg="http://v8.1c.ru/8.1/data/enterprise/current-config" xmlns:cmi="http://v8.1c.ru/8.2/managed-application/cmi" xmlns:ent="http://v8.1c.ru/8.1/data/enterprise" xmlns:lf="http://v8.1c.ru/8.2/managed-application/logform" xmlns:style="http://v8.1c.ru/8.1/data/ui/style" xmlns:sys="http://v8.1c.ru/8.1/data/ui/fonts/system" xmlns:v8="http://v8.1c.ru/8.1/data/core" xmlns:v8ui="http://v8.1c.ru/8.1/data/ui" xmlns:web="http://v8.1c.ru/8.1/data/ui/colors/web" xmlns:win="http://v8.1c.ru/8.1/data/ui/colors/windows" xmlns:xen="http://v8.1c.ru/8.3/xcf/enums" xmlns:xpr="http://v8.1c.ru/8.3/xcf/predef" xmlns:xr="http://v8.1c.ru/8.3/xcf/readable" xmlns:xs="http://www.w3.org/2001/XMLSchema" xmlns:xsi="http://www.w3.org/2001/XMLSchema-instance" version="2.4">
	<ExchangePlan uuid="bcec85b7-c794-4f13-86a6-772f276b36ae">
		<InternalInfo>
			<xr:ThisNode>1e94ea4e-25f5-414c-b389-cb3a11d15490</xr:ThisNode>
			<xr:GeneratedType name="ExchangePlanObject.ОбменЭлмаПартком83" category="Object">
				<xr:TypeId>bf36969f-e85b-4628-9e37-420e72535615</xr:TypeId>
				<xr:ValueId>94f68e4e-1c2d-4fdb-a4a0-6377bf088e08</xr:ValueId>
			</xr:GeneratedType>
			<xr:GeneratedType name="ExchangePlanRef.ОбменЭлмаПартком83" category="Ref">
				<xr:TypeId>de24bac6-e2cd-453a-bbaa-ce3c2811baee</xr:TypeId>
				<xr:ValueId>a12485d2-b712-476e-b2cb-600931487e67</xr:ValueId>
			</xr:GeneratedType>
			<xr:GeneratedType name="ExchangePlanSelection.ОбменЭлмаПартком83" category="Selection">
				<xr:TypeId>b8976b9d-34b3-4b11-822f-bd5bdf8828dc</xr:TypeId>
				<xr:ValueId>d90dd1c0-25ad-48b5-8a35-81e4dd569628</xr:ValueId>
			</xr:GeneratedType>
			<xr:GeneratedType name="ExchangePlanList.ОбменЭлмаПартком83" category="List">
				<xr:TypeId>30e6ea82-3895-472d-b1bf-a729aed696ba</xr:TypeId>
				<xr:ValueId>2fe32049-dbca-4598-ad33-569f8a3bf6c9</xr:ValueId>
			</xr:GeneratedType>
			<xr:GeneratedType name="ExchangePlanManager.ОбменЭлмаПартком83" category="Manager">
				<xr:TypeId>c369591d-2895-42be-8dd9-9cdbc04afb10</xr:TypeId>
				<xr:ValueId>98d5fa4c-d6dc-42ef-b078-236d951ea73c</xr:ValueId>
			</xr:GeneratedType>
		</InternalInfo>
		<Properties>
			<Name>ОбменЭлмаПартком83</Name>
			<Synonym>
				<v8:item>
					<v8:lang>ru</v8:lang>
					<v8:content>Обмен "Элма" -&gt; "ПартКом 8.3"</v8:content>
				</v8:item>
			</Synonym>
			<Comment/>
			<UseStandardCommands>false</UseStandardCommands>
			<CodeLength>9</CodeLength>
			<CodeAllowedLength>Variable</CodeAllowedLength>
			<DescriptionLength>25</DescriptionLength>
			<DefaultPresentation>AsDescription</DefaultPresentation>
			<EditType>InDialog</EditType>
			<QuickChoice>false</QuickChoice>
			<ChoiceMode>BothWays</ChoiceMode>
			<InputByString>
				<xr:Field>ExchangePlan.ОбменЭлмаПартком83.StandardAttribute.Description</xr:Field>
				<xr:Field>ExchangePlan.ОбменЭлмаПартком83.StandardAttribute.Code</xr:Field>
			</InputByString>
			<SearchStringModeOnInputByString>Begin</SearchStringModeOnInputByString>
			<FullTextSearchOnInputByString>DontUse</FullTextSearchOnInputByString>
			<ChoiceDataGetModeOnInputByString>Directly</ChoiceDataGetModeOnInputByString>
			<DefaultObjectForm/>
			<DefaultListForm/>
			<DefaultChoiceForm/>
			<AuxiliaryObjectForm/>
			<AuxiliaryListForm/>
			<AuxiliaryChoiceForm/>
			<Characteristics/>
			<BasedOn/>
			<DistributedInfoBase>false</DistributedInfoBase>
			<CreateOnInput>DontUse</CreateOnInput>
			<ChoiceHistoryOnInput>Auto</ChoiceHistoryOnInput>
			<IncludeHelpInContents>false</IncludeHelpInContents>
			<DataLockFields/>
			<DataLockControlMode>Managed</DataLockControlMode>
			<FullTextSearch>Use</FullTextSearch>
			<ObjectPresentation/>
			<ExtendedObjectPresentation/>
			<ListPresentation/>
			<ExtendedListPresentation/>
			<Explanation/>
		</Properties>
		<ChildObjects>
			<Attribute uuid="d9050cd5-318a-4d56-9aa9-382c62a041be">
				<Properties>
					<Name>ИдентификаторУзла</Name>
					<Synonym>
						<v8:item>
							<v8:lang>ru</v8:lang>
							<v8:content>Идентификатор узла</v8:content>
						</v8:item>
					</Synonym>
					<Comment/>
					<Type>
						<v8:Type>xs:decimal</v8:Type>
						<v8:NumberQualifiers>
							<v8:Digits>3</v8:Digits>
							<v8:FractionDigits>0</v8:FractionDigits>
							<v8:AllowedSign>Nonnegative</v8:AllowedSign>
						</v8:NumberQualifiers>
					</Type>
					<PasswordMode>false</PasswordMode>
					<Format/>
					<EditFormat/>
					<ToolTip/>
					<MarkNegatives>false</MarkNegatives>
					<Mask/>
					<MultiLine>false</MultiLine>
					<ExtendedEdit>false</ExtendedEdit>
					<MinValue xsi:nil="true"/>
					<MaxValue xsi:nil="true"/>
					<FillFromFillingValue>false</FillFromFillingValue>
					<FillValue xsi:nil="true"/>
					<FillChecking>DontCheck</FillChecking>
					<ChoiceFoldersAndItems>Items</ChoiceFoldersAndItems>
					<ChoiceParameterLinks/>
					<ChoiceParameters/>
					<QuickChoice>Auto</QuickChoice>
					<CreateOnInput>Auto</CreateOnInput>
					<ChoiceForm/>
					<LinkByType/>
					<ChoiceHistoryOnInput>Auto</ChoiceHistoryOnInput>
					<Indexing>DontIndex</Indexing>
					<FullTextSearch>Use</FullTextSearch>
				</Properties>
			</Attribute>
			<Attribute uuid="6e89b0f2-460c-4441-ad6c-fbb5e5501e42">
				<Properties>
					<Name>Входящий</Name>
					<Synonym>
						<v8:item>
							<v8:lang>ru</v8:lang>
							<v8:content>Входящий</v8:content>
						</v8:item>
					</Synonym>
					<Comment/>
					<Type>
						<v8:Type>xs:boolean</v8:Type>
					</Type>
					<PasswordMode>false</PasswordMode>
					<Format/>
					<EditFormat/>
					<ToolTip/>
					<MarkNegatives>false</MarkNegatives>
					<Mask/>
					<MultiLine>false</MultiLine>
					<ExtendedEdit>false</ExtendedEdit>
					<MinValue xsi:nil="true"/>
					<MaxValue xsi:nil="true"/>
					<FillFromFillingValue>false</FillFromFillingValue>
					<FillValue xsi:nil="true"/>
					<FillChecking>DontCheck</FillChecking>
					<ChoiceFoldersAndItems>Items</ChoiceFoldersAndItems>
					<ChoiceParameterLinks/>
					<ChoiceParameters/>
					<QuickChoice>Auto</QuickChoice>
					<CreateOnInput>Auto</CreateOnInput>
					<ChoiceForm/>
					<LinkByType/>
					<ChoiceHistoryOnInput>Auto</ChoiceHistoryOnInput>
					<Indexing>DontIndex</Indexing>
					<FullTextSearch>Use</FullTextSearch>
				</Properties>
			</Attribute>
			<Attribute uuid="34f42e95-633e-47d2-a3d4-240f57f4617e">
				<Properties>
					<Name>Исходящий</Name>
					<Synonym>
						<v8:item>
							<v8:lang>ru</v8:lang>
							<v8:content>Исходящий</v8:content>
						</v8:item>
					</Synonym>
					<Comment/>
					<Type>
						<v8:Type>xs:boolean</v8:Type>
					</Type>
					<PasswordMode>false</PasswordMode>
					<Format/>
					<EditFormat/>
					<ToolTip/>
					<MarkNegatives>false</MarkNegatives>
					<Mask/>
					<MultiLine>false</MultiLine>
					<ExtendedEdit>false</ExtendedEdit>
					<MinValue xsi:nil="true"/>
					<MaxValue xsi:nil="true"/>
					<FillFromFillingValue>false</FillFromFillingValue>
					<FillValue xsi:nil="true"/>
					<FillChecking>DontCheck</FillChecking>
					<ChoiceFoldersAndItems>Items</ChoiceFoldersAndItems>
					<ChoiceParameterLinks/>
					<ChoiceParameters/>
					<QuickChoice>Auto</QuickChoice>
					<CreateOnInput>Auto</CreateOnInput>
					<ChoiceForm/>
					<LinkByType/>
					<ChoiceHistoryOnInput>Auto</ChoiceHistoryOnInput>
					<Indexing>DontIndex</Indexing>
					<FullTextSearch>Use</FullTextSearch>
				</Properties>
			</Attribute>
		</ChildObjects>
	</ExchangePlan>
</MetaDataObject>